{"language":"Java","type":"CompilationUnit","pid":{"type":"MemberExpression","object":{"type":"MemberExpression","object":{"type":"MemberExpression","object":{"type":"MemberExpression","object":{"type":"Identifier","name":"org","loc":{"start":{"line":2},"end":{"line":2}}},"property":{"type":"Identifier","name":"owasp"},"loc":{"start":{"line":2},"end":{"line":2}}},"property":{"type":"Identifier","name":"webgoat"},"loc":{"start":{"line":2},"end":{"line":2}}},"property":{"type":"Identifier","name":"lessons"},"loc":{"start":{"line":2},"end":{"line":2}}},"property":{"type":"Identifier","name":"RoleBasedAccessControl"},"loc":{"start":{"line":2},"end":{"line":2}}},"annotations":[],"definitions":[{"type":"Import","qualid":{"type":"MemberExpression","object":{"type":"MemberExpression","object":{"type":"Identifier","name":"java","loc":{"start":{"line":4},"end":{"line":4}}},"property":{"type":"Identifier","name":"sql"},"loc":{"start":{"line":4},"end":{"line":4}}},"property":{"type":"Identifier","name":"PreparedStatement"},"loc":{"start":{"line":4},"end":{"line":4}}}},{"type":"Import","qualid":{"type":"MemberExpression","object":{"type":"MemberExpression","object":{"type":"Identifier","name":"java","loc":{"start":{"line":5},"end":{"line":5}}},"property":{"type":"Identifier","name":"sql"},"loc":{"start":{"line":5},"end":{"line":5}}},"property":{"type":"Identifier","name":"ResultSet"},"loc":{"start":{"line":5},"end":{"line":5}}}},{"type":"Import","qualid":{"type":"MemberExpression","object":{"type":"MemberExpression","object":{"type":"Identifier","name":"java","loc":{"start":{"line":6},"end":{"line":6}}},"property":{"type":"Identifier","name":"sql"},"loc":{"start":{"line":6},"end":{"line":6}}},"property":{"type":"Identifier","name":"SQLException"},"loc":{"start":{"line":6},"end":{"line":6}}}},{"type":"Import","qualid":{"type":"MemberExpression","object":{"type":"MemberExpression","object":{"type":"MemberExpression","object":{"type":"MemberExpression","object":{"type":"MemberExpression","object":{"type":"Identifier","name":"org","loc":{"start":{"line":7},"end":{"line":7}}},"property":{"type":"Identifier","name":"owasp"},"loc":{"start":{"line":7},"end":{"line":7}}},"property":{"type":"Identifier","name":"webgoat"},"loc":{"start":{"line":7},"end":{"line":7}}},"property":{"type":"Identifier","name":"lessons"},"loc":{"start":{"line":7},"end":{"line":7}}},"property":{"type":"Identifier","name":"GoatHillsFinancial"},"loc":{"start":{"line":7},"end":{"line":7}}},"property":{"type":"Identifier","name":"DefaultLessonAction"},"loc":{"start":{"line":7},"end":{"line":7}}}},{"type":"Import","qualid":{"type":"MemberExpression","object":{"type":"MemberExpression","object":{"type":"MemberExpression","object":{"type":"MemberExpression","object":{"type":"MemberExpression","object":{"type":"Identifier","name":"org","loc":{"start":{"line":8},"end":{"line":8}}},"property":{"type":"Identifier","name":"owasp"},"loc":{"start":{"line":8},"end":{"line":8}}},"property":{"type":"Identifier","name":"webgoat"},"loc":{"start":{"line":8},"end":{"line":8}}},"property":{"type":"Identifier","name":"lessons"},"loc":{"start":{"line":8},"end":{"line":8}}},"property":{"type":"Identifier","name":"GoatHillsFinancial"},"loc":{"start":{"line":8},"end":{"line":8}}},"property":{"type":"Identifier","name":"GoatHillsFinancial"},"loc":{"start":{"line":8},"end":{"line":8}}}},{"type":"Import","qualid":{"type":"MemberExpression","object":{"type":"MemberExpression","object":{"type":"MemberExpression","object":{"type":"MemberExpression","object":{"type":"Identifier","name":"org","loc":{"start":{"line":9},"end":{"line":9}}},"property":{"type":"Identifier","name":"owasp"},"loc":{"start":{"line":9},"end":{"line":9}}},"property":{"type":"Identifier","name":"webgoat"},"loc":{"start":{"line":9},"end":{"line":9}}},"property":{"type":"Identifier","name":"session"},"loc":{"start":{"line":9},"end":{"line":9}}},"property":{"type":"Identifier","name":"Employee"},"loc":{"start":{"line":9},"end":{"line":9}}}},{"type":"Import","qualid":{"type":"MemberExpression","object":{"type":"MemberExpression","object":{"type":"MemberExpression","object":{"type":"MemberExpression","object":{"type":"Identifier","name":"org","loc":{"start":{"line":10},"end":{"line":10}}},"property":{"type":"Identifier","name":"owasp"},"loc":{"start":{"line":10},"end":{"line":10}}},"property":{"type":"Identifier","name":"webgoat"},"loc":{"start":{"line":10},"end":{"line":10}}},"property":{"type":"Identifier","name":"session"},"loc":{"start":{"line":10},"end":{"line":10}}},"property":{"type":"Identifier","name":"ParameterNotFoundException"},"loc":{"start":{"line":10},"end":{"line":10}}}},{"type":"Import","qualid":{"type":"MemberExpression","object":{"type":"MemberExpression","object":{"type":"MemberExpression","object":{"type":"MemberExpression","object":{"type":"Identifier","name":"org","loc":{"start":{"line":11},"end":{"line":11}}},"property":{"type":"Identifier","name":"owasp"},"loc":{"start":{"line":11},"end":{"line":11}}},"property":{"type":"Identifier","name":"webgoat"},"loc":{"start":{"line":11},"end":{"line":11}}},"property":{"type":"Identifier","name":"session"},"loc":{"start":{"line":11},"end":{"line":11}}},"property":{"type":"Identifier","name":"UnauthenticatedException"},"loc":{"start":{"line":11},"end":{"line":11}}}},{"type":"Import","qualid":{"type":"MemberExpression","object":{"type":"MemberExpression","object":{"type":"MemberExpression","object":{"type":"MemberExpression","object":{"type":"Identifier","name":"org","loc":{"start":{"line":12},"end":{"line":12}}},"property":{"type":"Identifier","name":"owasp"},"loc":{"start":{"line":12},"end":{"line":12}}},"property":{"type":"Identifier","name":"webgoat"},"loc":{"start":{"line":12},"end":{"line":12}}},"property":{"type":"Identifier","name":"session"},"loc":{"start":{"line":12},"end":{"line":12}}},"property":{"type":"Identifier","name":"UnauthorizedException"},"loc":{"start":{"line":12},"end":{"line":12}}}},{"type":"Import","qualid":{"type":"MemberExpression","object":{"type":"MemberExpression","object":{"type":"MemberExpression","object":{"type":"MemberExpression","object":{"type":"Identifier","name":"org","loc":{"start":{"line":13},"end":{"line":13}}},"property":{"type":"Identifier","name":"owasp"},"loc":{"start":{"line":13},"end":{"line":13}}},"property":{"type":"Identifier","name":"webgoat"},"loc":{"start":{"line":13},"end":{"line":13}}},"property":{"type":"Identifier","name":"session"},"loc":{"start":{"line":13},"end":{"line":13}}},"property":{"type":"Identifier","name":"WebSession"},"loc":{"start":{"line":13},"end":{"line":13}}}},{"type":"ClassDeclaration","id":{"type":"Identifier","name":"EditProfile"},"modifiers":{"type":"Modifiers","modifiers":["public"],"annotations":[]},"extending":{"type":"Identifier","name":"DefaultLessonAction","loc":{"start":{"line":43},"end":{"line":43}}},"definitions":[{"type":"FunctionDeclaration","id":{"type":"Identifier","name":"\u003cinit\u003e"},"modifiers":{"type":"Modifiers","modifiers":["public"],"annotations":[]},"typarams":[],"params":[{"type":"Identifier","name":"lesson","vartype":{"type":"Identifier","name":"GoatHillsFinancial","loc":{"start":{"line":46},"end":{"line":46}}}},{"type":"Identifier","name":"lessonName","vartype":{"type":"Identifier","name":"String","loc":{"start":{"line":46},"end":{"line":46}}}},{"type":"Identifier","name":"actionName","vartype":{"type":"Identifier","name":"String","loc":{"start":{"line":46},"end":{"line":46}}}}],"thrown":[],"body":{"type":"BlockStatement","body":[{"type":"ExpressionStatement","expression":{"type":"CallExpression","typeargs":[],"callee":{"type":"Identifier","name":"super","loc":{"start":{"line":48},"end":{"line":48}}},"arguments":[{"type":"Identifier","name":"lesson","loc":{"start":{"line":48},"end":{"line":48}}},{"type":"Identifier","name":"lessonName","loc":{"start":{"line":48},"end":{"line":48}}},{"type":"Identifier","name":"actionName","loc":{"start":{"line":48},"end":{"line":48}}}],"loc":{"start":{"line":48},"end":{"line":48}}},"loc":{"start":{"line":48},"end":{"line":48}}}],"loc":{"start":{"line":47},"end":{"line":49}}},"code":"\npublic \u003cinit\u003e(GoatHillsFinancial lesson, String lessonName, String actionName) {\n    super(lesson, lessonName, actionName);\n}","loc":{"start":{"line":46},"end":{"line":49}}},{"type":"FunctionDeclaration","id":{"type":"Identifier","name":"handleRequest"},"modifiers":{"type":"Modifiers","modifiers":["public"],"annotations":[]},"restype":{"type":"PrimitiveType"},"typarams":[],"params":[{"type":"Identifier","name":"s","vartype":{"type":"Identifier","name":"WebSession","loc":{"start":{"line":51},"end":{"line":51}}}}],"thrown":[{"type":"Identifier","name":"ParameterNotFoundException","loc":{"start":{"line":51},"end":{"line":51}}},{"type":"Identifier","name":"UnauthenticatedException","loc":{"start":{"line":51},"end":{"line":51}}},{"type":"Identifier","name":"UnauthorizedException","loc":{"start":{"line":52},"end":{"line":52}}}],"body":{"type":"BlockStatement","body":[{"type":"ExpressionStatement","expression":{"type":"CallExpression","typeargs":[],"callee":{"type":"MemberExpression","object":{"type":"CallExpression","typeargs":[],"callee":{"type":"Identifier","name":"getLesson","loc":{"start":{"line":54},"end":{"line":54}}},"arguments":[],"loc":{"start":{"line":54},"end":{"line":54}}},"property":{"type":"Identifier","name":"setCurrentAction"},"loc":{"start":{"line":54},"end":{"line":54}}},"arguments":[{"type":"Identifier","name":"s","loc":{"start":{"line":54},"end":{"line":54}}},{"type":"CallExpression","typeargs":[],"callee":{"type":"Identifier","name":"getActionName","loc":{"start":{"line":54},"end":{"line":54}}},"arguments":[],"loc":{"start":{"line":54},"end":{"line":54}}}],"loc":{"start":{"line":54},"end":{"line":54}}},"loc":{"start":{"line":54},"end":{"line":54}}},{"type":"IfStatement","test":{"type":"CallExpression","typeargs":[],"callee":{"type":"Identifier","name":"isAuthenticated","loc":{"start":{"line":56},"end":{"line":56}}},"arguments":[{"type":"Identifier","name":"s","loc":{"start":{"line":56},"end":{"line":56}}}],"loc":{"start":{"line":56},"end":{"line":56}}},"consequent":{"type":"BlockStatement","body":[{"type":"VariableDeclarator","id":{"type":"Identifier","name":"userId","vartype":{"type":"PrimitiveType"}},"modifiers":{"type":"Modifiers","modifiers":[],"annotations":[]},"vartype":{"type":"PrimitiveType"},"init":{"type":"CallExpression","typeargs":[],"callee":{"type":"Identifier","name":"getUserId","loc":{"start":{"line":58},"end":{"line":58}}},"arguments":[{"type":"Identifier","name":"s","loc":{"start":{"line":58},"end":{"line":58}}}],"loc":{"start":{"line":58},"end":{"line":58}}},"loc":{"start":{"line":58},"end":{"line":58}}},{"type":"VariableDeclarator","id":{"type":"Identifier","name":"employeeId","vartype":{"type":"PrimitiveType"}},"modifiers":{"type":"Modifiers","modifiers":[],"annotations":[]},"vartype":{"type":"PrimitiveType"},"init":{"type":"CallExpression","typeargs":[],"callee":{"type":"MemberExpression","object":{"type":"CallExpression","typeargs":[],"callee":{"type":"MemberExpression","object":{"type":"Identifier","name":"s","loc":{"start":{"line":59},"end":{"line":59}}},"property":{"type":"Identifier","name":"getParser"},"loc":{"start":{"line":59},"end":{"line":59}}},"arguments":[],"loc":{"start":{"line":59},"end":{"line":59}}},"property":{"type":"Identifier","name":"getIntParameter"},"loc":{"start":{"line":59},"end":{"line":59}}},"arguments":[{"type":"MemberExpression","object":{"type":"Identifier","name":"RoleBasedAccessControl","loc":{"start":{"line":59},"end":{"line":59}}},"property":{"type":"Identifier","name":"EMPLOYEE_ID"},"loc":{"start":{"line":59},"end":{"line":59}}}],"loc":{"start":{"line":59},"end":{"line":59}}},"loc":{"start":{"line":59},"end":{"line":59}}},{"type":"VariableDeclarator","id":{"type":"Identifier","name":"employee","vartype":{"type":"Identifier","name":"Employee","loc":{"start":{"line":61},"end":{"line":61}}}},"modifiers":{"type":"Modifiers","modifiers":[],"annotations":[]},"vartype":{"type":"Identifier","name":"Employee","loc":{"start":{"line":61},"end":{"line":61}}},"init":{"type":"CallExpression","typeargs":[],"callee":{"type":"Identifier","name":"getEmployeeProfile","loc":{"start":{"line":61},"end":{"line":61}}},"arguments":[{"type":"Identifier","name":"s","loc":{"start":{"line":61},"end":{"line":61}}},{"type":"Identifier","name":"userId","loc":{"start":{"line":61},"end":{"line":61}}},{"type":"Identifier","name":"employeeId","loc":{"start":{"line":61},"end":{"line":61}}}],"loc":{"start":{"line":61},"end":{"line":61}}},"loc":{"start":{"line":61},"end":{"line":61}}},{"type":"ExpressionStatement","expression":{"type":"CallExpression","typeargs":[],"callee":{"type":"Identifier","name":"setSessionAttribute","loc":{"start":{"line":62},"end":{"line":62}}},"arguments":[{"type":"Identifier","name":"s","loc":{"start":{"line":62},"end":{"line":62}}},{"type":"BinaryExpression","operator":"PLUS","left":{"type":"BinaryExpression","operator":"PLUS","left":{"type":"CallExpression","typeargs":[],"callee":{"type":"Identifier","name":"getLessonName","loc":{"start":{"line":62},"end":{"line":62}}},"arguments":[],"loc":{"start":{"line":62},"end":{"line":62}}},"right":{"type":"Literal","value":".","raw":"."},"loc":{"start":{"line":62},"end":{"line":62}}},"right":{"type":"MemberExpression","object":{"type":"Identifier","name":"RoleBasedAccessControl","loc":{"start":{"line":62},"end":{"line":62}}},"property":{"type":"Identifier","name":"EMPLOYEE_ATTRIBUTE_KEY"},"loc":{"start":{"line":62},"end":{"line":62}}},"loc":{"start":{"line":62},"end":{"line":62}}},{"type":"Identifier","name":"employee","loc":{"start":{"line":62},"end":{"line":62}}}],"loc":{"start":{"line":62},"end":{"line":62}}},"loc":{"start":{"line":62},"end":{"line":62}}}],"loc":{"start":{"line":57},"end":{"line":63}}},"alternate":{"type":"ThrowStatement","argument":{"type":"NewExpression","typeargs":[],"callee":{"type":"Identifier","name":"UnauthenticatedException","loc":{"start":{"line":65},"end":{"line":65}}},"arguments":[],"loc":{"start":{"line":65},"end":{"line":65}}},"loc":{"start":{"line":65},"end":{"line":65}}},"loc":{"start":{"line":56},"end":{"line":65}}}],"loc":{"start":{"line":53},"end":{"line":66}}},"code":"\npublic void handleRequest(WebSession s) throws ParameterNotFoundException, UnauthenticatedException, UnauthorizedException {\n    getLesson().setCurrentAction(s, getActionName());\n    if (isAuthenticated(s)) {\n        int userId \u003d getUserId(s);\n        int employeeId \u003d s.getParser().getIntParameter(RoleBasedAccessControl.EMPLOYEE_ID);\n        Employee employee \u003d getEmployeeProfile(s, userId, employeeId);\n        setSessionAttribute(s, getLessonName() + \".\" + RoleBasedAccessControl.EMPLOYEE_ATTRIBUTE_KEY, employee);\n    } else throw new UnauthenticatedException();\n}","loc":{"start":{"line":51},"end":{"line":66}}},{"type":"FunctionDeclaration","id":{"type":"Identifier","name":"getNextPage"},"modifiers":{"type":"Modifiers","modifiers":["public"],"annotations":[]},"restype":{"type":"Identifier","name":"String","loc":{"start":{"line":68},"end":{"line":68}}},"typarams":[],"params":[{"type":"Identifier","name":"s","vartype":{"type":"Identifier","name":"WebSession","loc":{"start":{"line":68},"end":{"line":68}}}}],"thrown":[],"body":{"type":"BlockStatement","body":[{"type":"ReturnStatement","argument":{"type":"MemberExpression","object":{"type":"Identifier","name":"RoleBasedAccessControl","loc":{"start":{"line":70},"end":{"line":70}}},"property":{"type":"Identifier","name":"EDITPROFILE_ACTION"},"loc":{"start":{"line":70},"end":{"line":70}}},"loc":{"start":{"line":70},"end":{"line":70}}}],"loc":{"start":{"line":69},"end":{"line":71}}},"code":"\npublic String getNextPage(WebSession s) {\n    return RoleBasedAccessControl.EDITPROFILE_ACTION;\n}","loc":{"start":{"line":68},"end":{"line":71}}},{"type":"FunctionDeclaration","id":{"type":"Identifier","name":"getEmployeeProfile"},"modifiers":{"type":"Modifiers","modifiers":["public"],"annotations":[]},"restype":{"type":"Identifier","name":"Employee","loc":{"start":{"line":73},"end":{"line":73}}},"typarams":[],"params":[{"type":"Identifier","name":"s","vartype":{"type":"Identifier","name":"WebSession","loc":{"start":{"line":73},"end":{"line":73}}}},{"type":"Identifier","name":"userId","vartype":{"type":"PrimitiveType"}},{"type":"Identifier","name":"subjectUserId","vartype":{"type":"PrimitiveType"}}],"thrown":[{"type":"Identifier","name":"UnauthorizedException","loc":{"start":{"line":73},"end":{"line":73}}}],"body":{"type":"BlockStatement","body":[{"type":"VariableDeclarator","id":{"type":"Identifier","name":"profile","vartype":{"type":"Identifier","name":"Employee","loc":{"start":{"line":75},"end":{"line":75}}}},"modifiers":{"type":"Modifiers","modifiers":[],"annotations":[]},"vartype":{"type":"Identifier","name":"Employee","loc":{"start":{"line":75},"end":{"line":75}}},"init":{"type":"Literal"},"loc":{"start":{"line":75},"end":{"line":75}}},{"type":"TryStatement","handlers":[{"type":"CatchClause","param":{"type":"Identifier","name":"e","vartype":{"type":"Identifier","name":"Exception","loc":{"start":{"line":108},"end":{"line":108}}}},"body":{"type":"BlockStatement","body":[{"type":"ExpressionStatement","expression":{"type":"CallExpression","typeargs":[],"callee":{"type":"MemberExpression","object":{"type":"Identifier","name":"s","loc":{"start":{"line":110},"end":{"line":110}}},"property":{"type":"Identifier","name":"setMessage"},"loc":{"start":{"line":110},"end":{"line":110}}},"arguments":[{"type":"Literal","value":"Error getting employee profile","raw":"Error getting employee profile"}],"loc":{"start":{"line":110},"end":{"line":110}}},"loc":{"start":{"line":110},"end":{"line":110}}},{"type":"ExpressionStatement","expression":{"type":"CallExpression","typeargs":[],"callee":{"type":"MemberExpression","object":{"type":"Identifier","name":"e","loc":{"start":{"line":111},"end":{"line":111}}},"property":{"type":"Identifier","name":"printStackTrace"},"loc":{"start":{"line":111},"end":{"line":111}}},"arguments":[],"loc":{"start":{"line":111},"end":{"line":111}}},"loc":{"start":{"line":111},"end":{"line":111}}}],"loc":{"start":{"line":109},"end":{"line":112}}},"loc":{"start":{"line":108},"end":{"line":112}}}],"block":{"type":"BlockStatement","body":[{"type":"VariableDeclarator","id":{"type":"Identifier","name":"query","vartype":{"type":"Identifier","name":"String","loc":{"start":{"line":80},"end":{"line":80}}}},"modifiers":{"type":"Modifiers","modifiers":[],"annotations":[]},"vartype":{"type":"Identifier","name":"String","loc":{"start":{"line":80},"end":{"line":80}}},"init":{"type":"Literal","value":"SELECT * FROM employee WHERE userid \u003d ?","raw":"SELECT * FROM employee WHERE userid \u003d ?"},"loc":{"start":{"line":80},"end":{"line":80}}},{"type":"TryStatement","handlers":[{"type":"CatchClause","param":{"type":"Identifier","name":"sqle","vartype":{"type":"Identifier","name":"SQLException","loc":{"start":{"line":103},"end":{"line":103}}}},"body":{"type":"BlockStatement","body":[{"type":"ExpressionStatement","expression":{"type":"CallExpression","typeargs":[],"callee":{"type":"MemberExpression","object":{"type":"Identifier","name":"s","loc":{"start":{"line":105},"end":{"line":105}}},"property":{"type":"Identifier","name":"setMessage"},"loc":{"start":{"line":105},"end":{"line":105}}},"arguments":[{"type":"Literal","value":"Error getting employee profile","raw":"Error getting employee profile"}],"loc":{"start":{"line":105},"end":{"line":105}}},"loc":{"start":{"line":105},"end":{"line":105}}},{"type":"ExpressionStatement","expression":{"type":"CallExpression","typeargs":[],"callee":{"type":"MemberExpression","object":{"type":"Identifier","name":"sqle","loc":{"start":{"line":106},"end":{"line":106}}},"property":{"type":"Identifier","name":"printStackTrace"},"loc":{"start":{"line":106},"end":{"line":106}}},"arguments":[],"loc":{"start":{"line":106},"end":{"line":106}}},"loc":{"start":{"line":106},"end":{"line":106}}}],"loc":{"start":{"line":104},"end":{"line":107}}},"loc":{"start":{"line":103},"end":{"line":107}}}],"block":{"type":"BlockStatement","body":[{"type":"VariableDeclarator","id":{"type":"Identifier","name":"answer_statement","vartype":{"type":"Identifier","name":"PreparedStatement","loc":{"start":{"line":84},"end":{"line":84}}}},"modifiers":{"type":"Modifiers","modifiers":[],"annotations":[]},"vartype":{"type":"Identifier","name":"PreparedStatement","loc":{"start":{"line":84},"end":{"line":84}}},"init":{"type":"CallExpression","typeargs":[],"callee":{"type":"MemberExpression","object":{"type":"CallExpression","typeargs":[],"callee":{"type":"MemberExpression","object":{"type":"Identifier","name":"WebSession","loc":{"start":{"line":84},"end":{"line":84}}},"property":{"type":"Identifier","name":"getConnection"},"loc":{"start":{"line":84},"end":{"line":84}}},"arguments":[{"type":"Identifier","name":"s","loc":{"start":{"line":84},"end":{"line":84}}}],"loc":{"start":{"line":84},"end":{"line":84}}},"property":{"type":"Identifier","name":"prepareStatement"},"loc":{"start":{"line":84},"end":{"line":85}}},"arguments":[{"type":"Identifier","name":"query","loc":{"start":{"line":85},"end":{"line":85}}},{"type":"MemberExpression","object":{"type":"Identifier","name":"ResultSet","loc":{"start":{"line":85},"end":{"line":85}}},"property":{"type":"Identifier","name":"TYPE_SCROLL_INSENSITIVE"},"loc":{"start":{"line":85},"end":{"line":85}}},{"type":"MemberExpression","object":{"type":"Identifier","name":"ResultSet","loc":{"start":{"line":85},"end":{"line":85}}},"property":{"type":"Identifier","name":"CONCUR_READ_ONLY"},"loc":{"start":{"line":85},"end":{"line":85}}}],"loc":{"start":{"line":84},"end":{"line":85}}},"loc":{"start":{"line":84},"end":{"line":85}}},{"type":"ExpressionStatement","expression":{"type":"CallExpression","typeargs":[],"callee":{"type":"MemberExpression","object":{"type":"Identifier","name":"answer_statement","loc":{"start":{"line":86},"end":{"line":86}}},"property":{"type":"Identifier","name":"setInt"},"loc":{"start":{"line":86},"end":{"line":86}}},"arguments":[{"type":"Literal","value":1,"raw":1},{"type":"Identifier","name":"subjectUserId","loc":{"start":{"line":86},"end":{"line":86}}}],"loc":{"start":{"line":86},"end":{"line":86}}},"loc":{"start":{"line":86},"end":{"line":86}}},{"type":"VariableDeclarator","id":{"type":"Identifier","name":"answer_results","vartype":{"type":"Identifier","name":"ResultSet","loc":{"start":{"line":87},"end":{"line":87}}}},"modifiers":{"type":"Modifiers","modifiers":[],"annotations":[]},"vartype":{"type":"Identifier","name":"ResultSet","loc":{"start":{"line":87},"end":{"line":87}}},"init":{"type":"CallExpression","typeargs":[],"callee":{"type":"MemberExpression","object":{"type":"Identifier","name":"answer_statement","loc":{"start":{"line":87},"end":{"line":87}}},"property":{"type":"Identifier","name":"executeQuery"},"loc":{"start":{"line":87},"end":{"line":87}}},"arguments":[],"loc":{"start":{"line":87},"end":{"line":87}}},"loc":{"start":{"line":87},"end":{"line":87}}},{"type":"IfStatement","test":{"type":"CallExpression","typeargs":[],"callee":{"type":"MemberExpression","object":{"type":"Identifier","name":"answer_results","loc":{"start":{"line":88},"end":{"line":88}}},"property":{"type":"Identifier","name":"next"},"loc":{"start":{"line":88},"end":{"line":88}}},"arguments":[],"loc":{"start":{"line":88},"end":{"line":88}}},"consequent":{"type":"BlockStatement","body":[{"type":"ExpressionStatement","expression":{"type":"AssignmentExpression","left":{"type":"Identifier","name":"profile","loc":{"start":{"line":91},"end":{"line":91}}},"right":{"type":"NewExpression","typeargs":[],"callee":{"type":"Identifier","name":"Employee","loc":{"start":{"line":91},"end":{"line":91}}},"arguments":[{"type":"CallExpression","typeargs":[],"callee":{"type":"MemberExpression","object":{"type":"Identifier","name":"answer_results","loc":{"start":{"line":91},"end":{"line":91}}},"property":{"type":"Identifier","name":"getInt"},"loc":{"start":{"line":91},"end":{"line":91}}},"arguments":[{"type":"Literal","value":"userid","raw":"userid"}],"loc":{"start":{"line":91},"end":{"line":91}}},{"type":"CallExpression","typeargs":[],"callee":{"type":"MemberExpression","object":{"type":"Identifier","name":"answer_results","loc":{"start":{"line":91},"end":{"line":91}}},"property":{"type":"Identifier","name":"getString"},"loc":{"start":{"line":91},"end":{"line":91}}},"arguments":[{"type":"Literal","value":"first_name","raw":"first_name"}],"loc":{"start":{"line":91},"end":{"line":91}}},{"type":"CallExpression","typeargs":[],"callee":{"type":"MemberExpression","object":{"type":"Identifier","name":"answer_results","loc":{"start":{"line":92},"end":{"line":92}}},"property":{"type":"Identifier","name":"getString"},"loc":{"start":{"line":92},"end":{"line":92}}},"arguments":[{"type":"Literal","value":"last_name","raw":"last_name"}],"loc":{"start":{"line":92},"end":{"line":92}}},{"type":"CallExpression","typeargs":[],"callee":{"type":"MemberExpression","object":{"type":"Identifier","name":"answer_results","loc":{"start":{"line":92},"end":{"line":92}}},"property":{"type":"Identifier","name":"getString"},"loc":{"start":{"line":92},"end":{"line":92}}},"arguments":[{"type":"Literal","value":"ssn","raw":"ssn"}],"loc":{"start":{"line":92},"end":{"line":92}}},{"type":"CallExpression","typeargs":[],"callee":{"type":"MemberExpression","object":{"type":"Identifier","name":"answer_results","loc":{"start":{"line":92},"end":{"line":92}}},"property":{"type":"Identifier","name":"getString"},"loc":{"start":{"line":92},"end":{"line":93}}},"arguments":[{"type":"Literal","value":"title","raw":"title"}],"loc":{"start":{"line":92},"end":{"line":93}}},{"type":"CallExpression","typeargs":[],"callee":{"type":"MemberExpression","object":{"type":"Identifier","name":"answer_results","loc":{"start":{"line":93},"end":{"line":93}}},"property":{"type":"Identifier","name":"getString"},"loc":{"start":{"line":93},"end":{"line":93}}},"arguments":[{"type":"Literal","value":"phone","raw":"phone"}],"loc":{"start":{"line":93},"end":{"line":93}}},{"type":"CallExpression","typeargs":[],"callee":{"type":"MemberExpression","object":{"type":"Identifier","name":"answer_results","loc":{"start":{"line":93},"end":{"line":93}}},"property":{"type":"Identifier","name":"getString"},"loc":{"start":{"line":93},"end":{"line":94}}},"arguments":[{"type":"Literal","value":"address1","raw":"address1"}],"loc":{"start":{"line":93},"end":{"line":94}}},{"type":"CallExpression","typeargs":[],"callee":{"type":"MemberExpression","object":{"type":"Identifier","name":"answer_results","loc":{"start":{"line":94},"end":{"line":94}}},"property":{"type":"Identifier","name":"getString"},"loc":{"start":{"line":94},"end":{"line":94}}},"arguments":[{"type":"Literal","value":"address2","raw":"address2"}],"loc":{"start":{"line":94},"end":{"line":94}}},{"type":"CallExpression","typeargs":[],"callee":{"type":"MemberExpression","object":{"type":"Identifier","name":"answer_results","loc":{"start":{"line":94},"end":{"line":94}}},"property":{"type":"Identifier","name":"getInt"},"loc":{"start":{"line":94},"end":{"line":95}}},"arguments":[{"type":"Literal","value":"manager","raw":"manager"}],"loc":{"start":{"line":94},"end":{"line":95}}},{"type":"CallExpression","typeargs":[],"callee":{"type":"MemberExpression","object":{"type":"Identifier","name":"answer_results","loc":{"start":{"line":95},"end":{"line":95}}},"property":{"type":"Identifier","name":"getString"},"loc":{"start":{"line":95},"end":{"line":95}}},"arguments":[{"type":"Literal","value":"start_date","raw":"start_date"}],"loc":{"start":{"line":95},"end":{"line":95}}},{"type":"CallExpression","typeargs":[],"callee":{"type":"MemberExpression","object":{"type":"Identifier","name":"answer_results","loc":{"start":{"line":95},"end":{"line":95}}},"property":{"type":"Identifier","name":"getInt"},"loc":{"start":{"line":95},"end":{"line":96}}},"arguments":[{"type":"Literal","value":"salary","raw":"salary"}],"loc":{"start":{"line":95},"end":{"line":96}}},{"type":"CallExpression","typeargs":[],"callee":{"type":"MemberExpression","object":{"type":"Identifier","name":"answer_results","loc":{"start":{"line":96},"end":{"line":96}}},"property":{"type":"Identifier","name":"getString"},"loc":{"start":{"line":96},"end":{"line":96}}},"arguments":[{"type":"Literal","value":"ccn","raw":"ccn"}],"loc":{"start":{"line":96},"end":{"line":96}}},{"type":"CallExpression","typeargs":[],"callee":{"type":"MemberExpression","object":{"type":"Identifier","name":"answer_results","loc":{"start":{"line":96},"end":{"line":96}}},"property":{"type":"Identifier","name":"getInt"},"loc":{"start":{"line":96},"end":{"line":97}}},"arguments":[{"type":"Literal","value":"ccn_limit","raw":"ccn_limit"}],"loc":{"start":{"line":96},"end":{"line":97}}},{"type":"CallExpression","typeargs":[],"callee":{"type":"MemberExpression","object":{"type":"Identifier","name":"answer_results","loc":{"start":{"line":97},"end":{"line":97}}},"property":{"type":"Identifier","name":"getString"},"loc":{"start":{"line":97},"end":{"line":97}}},"arguments":[{"type":"Literal","value":"disciplined_date","raw":"disciplined_date"}],"loc":{"start":{"line":97},"end":{"line":97}}},{"type":"CallExpression","typeargs":[],"callee":{"type":"MemberExpression","object":{"type":"Identifier","name":"answer_results","loc":{"start":{"line":97},"end":{"line":97}}},"property":{"type":"Identifier","name":"getString"},"loc":{"start":{"line":97},"end":{"line":98}}},"arguments":[{"type":"Literal","value":"disciplined_notes","raw":"disciplined_notes"}],"loc":{"start":{"line":97},"end":{"line":98}}},{"type":"CallExpression","typeargs":[],"callee":{"type":"MemberExpression","object":{"type":"Identifier","name":"answer_results","loc":{"start":{"line":98},"end":{"line":98}}},"property":{"type":"Identifier","name":"getString"},"loc":{"start":{"line":98},"end":{"line":98}}},"arguments":[{"type":"Literal","value":"personal_description","raw":"personal_description"}],"loc":{"start":{"line":98},"end":{"line":98}}}],"loc":{"start":{"line":91},"end":{"line":98}}},"loc":{"start":{"line":91},"end":{"line":98}}},"loc":{"start":{"line":91},"end":{"line":98}}}],"loc":{"start":{"line":89},"end":{"line":102}}},"loc":{"start":{"line":88},"end":{"line":102}}}],"loc":{"start":{"line":83},"end":{"line":103}}},"loc":{"start":{"line":82},"end":{"line":107}}}],"loc":{"start":{"line":79},"end":{"line":108}}},"loc":{"start":{"line":78},"end":{"line":112}}},{"type":"ReturnStatement","argument":{"type":"Identifier","name":"profile","loc":{"start":{"line":114},"end":{"line":114}}},"loc":{"start":{"line":114},"end":{"line":114}}}],"loc":{"start":{"line":74},"end":{"line":115}}},"code":"\npublic Employee getEmployeeProfile(WebSession s, int userId, int subjectUserId) throws UnauthorizedException {\n    Employee profile \u003d null;\n    try {\n        String query \u003d \"SELECT * FROM employee WHERE userid \u003d ?\";\n        try {\n            PreparedStatement answer_statement \u003d WebSession.getConnection(s).prepareStatement(query, ResultSet.TYPE_SCROLL_INSENSITIVE, ResultSet.CONCUR_READ_ONLY);\n            answer_statement.setInt(1, subjectUserId);\n            ResultSet answer_results \u003d answer_statement.executeQuery();\n            if (answer_results.next()) {\n                profile \u003d new Employee(answer_results.getInt(\"userid\"), answer_results.getString(\"first_name\"), answer_results.getString(\"last_name\"), answer_results.getString(\"ssn\"), answer_results.getString(\"title\"), answer_results.getString(\"phone\"), answer_results.getString(\"address1\"), answer_results.getString(\"address2\"), answer_results.getInt(\"manager\"), answer_results.getString(\"start_date\"), answer_results.getInt(\"salary\"), answer_results.getString(\"ccn\"), answer_results.getInt(\"ccn_limit\"), answer_results.getString(\"disciplined_date\"), answer_results.getString(\"disciplined_notes\"), answer_results.getString(\"personal_description\"));\n            }\n        } catch (SQLException sqle) {\n            s.setMessage(\"Error getting employee profile\");\n            sqle.printStackTrace();\n        }\n    } catch (Exception e) {\n        s.setMessage(\"Error getting employee profile\");\n        e.printStackTrace();\n    }\n    return profile;\n}","loc":{"start":{"line":73},"end":{"line":115}}},{"type":"FunctionDeclaration","id":{"type":"Identifier","name":"getEmployeeProfile_BACKUP"},"modifiers":{"type":"Modifiers","modifiers":["public"],"annotations":[]},"restype":{"type":"Identifier","name":"Employee","loc":{"start":{"line":117},"end":{"line":117}}},"typarams":[],"params":[{"type":"Identifier","name":"s","vartype":{"type":"Identifier","name":"WebSession","loc":{"start":{"line":117},"end":{"line":117}}}},{"type":"Identifier","name":"userId","vartype":{"type":"PrimitiveType"}},{"type":"Identifier","name":"subjectUserId","vartype":{"type":"PrimitiveType"}}],"thrown":[{"type":"Identifier","name":"UnauthorizedException","loc":{"start":{"line":117},"end":{"line":117}}}],"body":{"type":"BlockStatement","body":[{"type":"VariableDeclarator","id":{"type":"Identifier","name":"profile","vartype":{"type":"Identifier","name":"Employee","loc":{"start":{"line":123},"end":{"line":123}}}},"modifiers":{"type":"Modifiers","modifiers":[],"annotations":[]},"vartype":{"type":"Identifier","name":"Employee","loc":{"start":{"line":123},"end":{"line":123}}},"init":{"type":"Literal"},"loc":{"start":{"line":123},"end":{"line":123}}},{"type":"TryStatement","handlers":[{"type":"CatchClause","param":{"type":"Identifier","name":"e","vartype":{"type":"Identifier","name":"Exception","loc":{"start":{"line":156},"end":{"line":156}}}},"body":{"type":"BlockStatement","body":[{"type":"ExpressionStatement","expression":{"type":"CallExpression","typeargs":[],"callee":{"type":"MemberExpression","object":{"type":"Identifier","name":"s","loc":{"start":{"line":158},"end":{"line":158}}},"property":{"type":"Identifier","name":"setMessage"},"loc":{"start":{"line":158},"end":{"line":158}}},"arguments":[{"type":"Literal","value":"Error getting employee profile","raw":"Error getting employee profile"}],"loc":{"start":{"line":158},"end":{"line":158}}},"loc":{"start":{"line":158},"end":{"line":158}}},{"type":"ExpressionStatement","expression":{"type":"CallExpression","typeargs":[],"callee":{"type":"MemberExpression","object":{"type":"Identifier","name":"e","loc":{"start":{"line":159},"end":{"line":159}}},"property":{"type":"Identifier","name":"printStackTrace"},"loc":{"start":{"line":159},"end":{"line":159}}},"arguments":[],"loc":{"start":{"line":159},"end":{"line":159}}},"loc":{"start":{"line":159},"end":{"line":159}}}],"loc":{"start":{"line":157},"end":{"line":160}}},"loc":{"start":{"line":156},"end":{"line":160}}}],"block":{"type":"BlockStatement","body":[{"type":"VariableDeclarator","id":{"type":"Identifier","name":"query","vartype":{"type":"Identifier","name":"String","loc":{"start":{"line":128},"end":{"line":128}}}},"modifiers":{"type":"Modifiers","modifiers":[],"annotations":[]},"vartype":{"type":"Identifier","name":"String","loc":{"start":{"line":128},"end":{"line":128}}},"init":{"type":"Literal","value":"SELECT * FROM employee WHERE userid \u003d ?","raw":"SELECT * FROM employee WHERE userid \u003d ?"},"loc":{"start":{"line":128},"end":{"line":128}}},{"type":"TryStatement","handlers":[{"type":"CatchClause","param":{"type":"Identifier","name":"sqle","vartype":{"type":"Identifier","name":"SQLException","loc":{"start":{"line":151},"end":{"line":151}}}},"body":{"type":"BlockStatement","body":[{"type":"ExpressionStatement","expression":{"type":"CallExpression","typeargs":[],"callee":{"type":"MemberExpression","object":{"type":"Identifier","name":"s","loc":{"start":{"line":153},"end":{"line":153}}},"property":{"type":"Identifier","name":"setMessage"},"loc":{"start":{"line":153},"end":{"line":153}}},"arguments":[{"type":"Literal","value":"Error getting employee profile","raw":"Error getting employee profile"}],"loc":{"start":{"line":153},"end":{"line":153}}},"loc":{"start":{"line":153},"end":{"line":153}}},{"type":"ExpressionStatement","expression":{"type":"CallExpression","typeargs":[],"callee":{"type":"MemberExpression","object":{"type":"Identifier","name":"sqle","loc":{"start":{"line":154},"end":{"line":154}}},"property":{"type":"Identifier","name":"printStackTrace"},"loc":{"start":{"line":154},"end":{"line":154}}},"arguments":[],"loc":{"start":{"line":154},"end":{"line":154}}},"loc":{"start":{"line":154},"end":{"line":154}}}],"loc":{"start":{"line":152},"end":{"line":155}}},"loc":{"start":{"line":151},"end":{"line":155}}}],"block":{"type":"BlockStatement","body":[{"type":"VariableDeclarator","id":{"type":"Identifier","name":"answer_statement","vartype":{"type":"Identifier","name":"PreparedStatement","loc":{"start":{"line":132},"end":{"line":132}}}},"modifiers":{"type":"Modifiers","modifiers":[],"annotations":[]},"vartype":{"type":"Identifier","name":"PreparedStatement","loc":{"start":{"line":132},"end":{"line":132}}},"init":{"type":"CallExpression","typeargs":[],"callee":{"type":"MemberExpression","object":{"type":"CallExpression","typeargs":[],"callee":{"type":"MemberExpression","object":{"type":"Identifier","name":"WebSession","loc":{"start":{"line":132},"end":{"line":132}}},"property":{"type":"Identifier","name":"getConnection"},"loc":{"start":{"line":132},"end":{"line":132}}},"arguments":[{"type":"Identifier","name":"s","loc":{"start":{"line":132},"end":{"line":132}}}],"loc":{"start":{"line":132},"end":{"line":132}}},"property":{"type":"Identifier","name":"prepareStatement"},"loc":{"start":{"line":132},"end":{"line":133}}},"arguments":[{"type":"Identifier","name":"query","loc":{"start":{"line":133},"end":{"line":133}}},{"type":"MemberExpression","object":{"type":"Identifier","name":"ResultSet","loc":{"start":{"line":133},"end":{"line":133}}},"property":{"type":"Identifier","name":"TYPE_SCROLL_INSENSITIVE"},"loc":{"start":{"line":133},"end":{"line":133}}},{"type":"MemberExpression","object":{"type":"Identifier","name":"ResultSet","loc":{"start":{"line":133},"end":{"line":133}}},"property":{"type":"Identifier","name":"CONCUR_READ_ONLY"},"loc":{"start":{"line":133},"end":{"line":133}}}],"loc":{"start":{"line":132},"end":{"line":133}}},"loc":{"start":{"line":132},"end":{"line":133}}},{"type":"ExpressionStatement","expression":{"type":"CallExpression","typeargs":[],"callee":{"type":"MemberExpression","object":{"type":"Identifier","name":"answer_statement","loc":{"start":{"line":134},"end":{"line":134}}},"property":{"type":"Identifier","name":"setInt"},"loc":{"start":{"line":134},"end":{"line":134}}},"arguments":[{"type":"Literal","value":1,"raw":1},{"type":"Identifier","name":"subjectUserId","loc":{"start":{"line":134},"end":{"line":134}}}],"loc":{"start":{"line":134},"end":{"line":134}}},"loc":{"start":{"line":134},"end":{"line":134}}},{"type":"VariableDeclarator","id":{"type":"Identifier","name":"answer_results","vartype":{"type":"Identifier","name":"ResultSet","loc":{"start":{"line":135},"end":{"line":135}}}},"modifiers":{"type":"Modifiers","modifiers":[],"annotations":[]},"vartype":{"type":"Identifier","name":"ResultSet","loc":{"start":{"line":135},"end":{"line":135}}},"init":{"type":"CallExpression","typeargs":[],"callee":{"type":"MemberExpression","object":{"type":"Identifier","name":"answer_statement","loc":{"start":{"line":135},"end":{"line":135}}},"property":{"type":"Identifier","name":"executeQuery"},"loc":{"start":{"line":135},"end":{"line":135}}},"arguments":[],"loc":{"start":{"line":135},"end":{"line":135}}},"loc":{"start":{"line":135},"end":{"line":135}}},{"type":"IfStatement","test":{"type":"CallExpression","typeargs":[],"callee":{"type":"MemberExpression","object":{"type":"Identifier","name":"answer_results","loc":{"start":{"line":136},"end":{"line":136}}},"property":{"type":"Identifier","name":"next"},"loc":{"start":{"line":136},"end":{"line":136}}},"arguments":[],"loc":{"start":{"line":136},"end":{"line":136}}},"consequent":{"type":"BlockStatement","body":[{"type":"ExpressionStatement","expression":{"type":"AssignmentExpression","left":{"type":"Identifier","name":"profile","loc":{"start":{"line":139},"end":{"line":139}}},"right":{"type":"NewExpression","typeargs":[],"callee":{"type":"Identifier","name":"Employee","loc":{"start":{"line":139},"end":{"line":139}}},"arguments":[{"type":"CallExpression","typeargs":[],"callee":{"type":"MemberExpression","object":{"type":"Identifier","name":"answer_results","loc":{"start":{"line":139},"end":{"line":139}}},"property":{"type":"Identifier","name":"getInt"},"loc":{"start":{"line":139},"end":{"line":139}}},"arguments":[{"type":"Literal","value":"userid","raw":"userid"}],"loc":{"start":{"line":139},"end":{"line":139}}},{"type":"CallExpression","typeargs":[],"callee":{"type":"MemberExpression","object":{"type":"Identifier","name":"answer_results","loc":{"start":{"line":139},"end":{"line":139}}},"property":{"type":"Identifier","name":"getString"},"loc":{"start":{"line":139},"end":{"line":139}}},"arguments":[{"type":"Literal","value":"first_name","raw":"first_name"}],"loc":{"start":{"line":139},"end":{"line":139}}},{"type":"CallExpression","typeargs":[],"callee":{"type":"MemberExpression","object":{"type":"Identifier","name":"answer_results","loc":{"start":{"line":140},"end":{"line":140}}},"property":{"type":"Identifier","name":"getString"},"loc":{"start":{"line":140},"end":{"line":140}}},"arguments":[{"type":"Literal","value":"last_name","raw":"last_name"}],"loc":{"start":{"line":140},"end":{"line":140}}},{"type":"CallExpression","typeargs":[],"callee":{"type":"MemberExpression","object":{"type":"Identifier","name":"answer_results","loc":{"start":{"line":140},"end":{"line":140}}},"property":{"type":"Identifier","name":"getString"},"loc":{"start":{"line":140},"end":{"line":140}}},"arguments":[{"type":"Literal","value":"ssn","raw":"ssn"}],"loc":{"start":{"line":140},"end":{"line":140}}},{"type":"CallExpression","typeargs":[],"callee":{"type":"MemberExpression","object":{"type":"Identifier","name":"answer_results","loc":{"start":{"line":140},"end":{"line":140}}},"property":{"type":"Identifier","name":"getString"},"loc":{"start":{"line":140},"end":{"line":141}}},"arguments":[{"type":"Literal","value":"title","raw":"title"}],"loc":{"start":{"line":140},"end":{"line":141}}},{"type":"CallExpression","typeargs":[],"callee":{"type":"MemberExpression","object":{"type":"Identifier","name":"answer_results","loc":{"start":{"line":141},"end":{"line":141}}},"property":{"type":"Identifier","name":"getString"},"loc":{"start":{"line":141},"end":{"line":141}}},"arguments":[{"type":"Literal","value":"phone","raw":"phone"}],"loc":{"start":{"line":141},"end":{"line":141}}},{"type":"CallExpression","typeargs":[],"callee":{"type":"MemberExpression","object":{"type":"Identifier","name":"answer_results","loc":{"start":{"line":141},"end":{"line":141}}},"property":{"type":"Identifier","name":"getString"},"loc":{"start":{"line":141},"end":{"line":142}}},"arguments":[{"type":"Literal","value":"address1","raw":"address1"}],"loc":{"start":{"line":141},"end":{"line":142}}},{"type":"CallExpression","typeargs":[],"callee":{"type":"MemberExpression","object":{"type":"Identifier","name":"answer_results","loc":{"start":{"line":142},"end":{"line":142}}},"property":{"type":"Identifier","name":"getString"},"loc":{"start":{"line":142},"end":{"line":142}}},"arguments":[{"type":"Literal","value":"address2","raw":"address2"}],"loc":{"start":{"line":142},"end":{"line":142}}},{"type":"CallExpression","typeargs":[],"callee":{"type":"MemberExpression","object":{"type":"Identifier","name":"answer_results","loc":{"start":{"line":142},"end":{"line":142}}},"property":{"type":"Identifier","name":"getInt"},"loc":{"start":{"line":142},"end":{"line":143}}},"arguments":[{"type":"Literal","value":"manager","raw":"manager"}],"loc":{"start":{"line":142},"end":{"line":143}}},{"type":"CallExpression","typeargs":[],"callee":{"type":"MemberExpression","object":{"type":"Identifier","name":"answer_results","loc":{"start":{"line":143},"end":{"line":143}}},"property":{"type":"Identifier","name":"getString"},"loc":{"start":{"line":143},"end":{"line":143}}},"arguments":[{"type":"Literal","value":"start_date","raw":"start_date"}],"loc":{"start":{"line":143},"end":{"line":143}}},{"type":"CallExpression","typeargs":[],"callee":{"type":"MemberExpression","object":{"type":"Identifier","name":"answer_results","loc":{"start":{"line":143},"end":{"line":143}}},"property":{"type":"Identifier","name":"getInt"},"loc":{"start":{"line":143},"end":{"line":144}}},"arguments":[{"type":"Literal","value":"salary","raw":"salary"}],"loc":{"start":{"line":143},"end":{"line":144}}},{"type":"CallExpression","typeargs":[],"callee":{"type":"MemberExpression","object":{"type":"Identifier","name":"answer_results","loc":{"start":{"line":144},"end":{"line":144}}},"property":{"type":"Identifier","name":"getString"},"loc":{"start":{"line":144},"end":{"line":144}}},"arguments":[{"type":"Literal","value":"ccn","raw":"ccn"}],"loc":{"start":{"line":144},"end":{"line":144}}},{"type":"CallExpression","typeargs":[],"callee":{"type":"MemberExpression","object":{"type":"Identifier","name":"answer_results","loc":{"start":{"line":144},"end":{"line":144}}},"property":{"type":"Identifier","name":"getInt"},"loc":{"start":{"line":144},"end":{"line":145}}},"arguments":[{"type":"Literal","value":"ccn_limit","raw":"ccn_limit"}],"loc":{"start":{"line":144},"end":{"line":145}}},{"type":"CallExpression","typeargs":[],"callee":{"type":"MemberExpression","object":{"type":"Identifier","name":"answer_results","loc":{"start":{"line":145},"end":{"line":145}}},"property":{"type":"Identifier","name":"getString"},"loc":{"start":{"line":145},"end":{"line":145}}},"arguments":[{"type":"Literal","value":"disciplined_date","raw":"disciplined_date"}],"loc":{"start":{"line":145},"end":{"line":145}}},{"type":"CallExpression","typeargs":[],"callee":{"type":"MemberExpression","object":{"type":"Identifier","name":"answer_results","loc":{"start":{"line":145},"end":{"line":145}}},"property":{"type":"Identifier","name":"getString"},"loc":{"start":{"line":145},"end":{"line":146}}},"arguments":[{"type":"Literal","value":"disciplined_notes","raw":"disciplined_notes"}],"loc":{"start":{"line":145},"end":{"line":146}}},{"type":"CallExpression","typeargs":[],"callee":{"type":"MemberExpression","object":{"type":"Identifier","name":"answer_results","loc":{"start":{"line":146},"end":{"line":146}}},"property":{"type":"Identifier","name":"getString"},"loc":{"start":{"line":146},"end":{"line":146}}},"arguments":[{"type":"Literal","value":"personal_description","raw":"personal_description"}],"loc":{"start":{"line":146},"end":{"line":146}}}],"loc":{"start":{"line":139},"end":{"line":146}}},"loc":{"start":{"line":139},"end":{"line":146}}},"loc":{"start":{"line":139},"end":{"line":146}}}],"loc":{"start":{"line":137},"end":{"line":150}}},"loc":{"start":{"line":136},"end":{"line":150}}}],"loc":{"start":{"line":131},"end":{"line":151}}},"loc":{"start":{"line":130},"end":{"line":155}}}],"loc":{"start":{"line":127},"end":{"line":156}}},"loc":{"start":{"line":126},"end":{"line":160}}},{"type":"ReturnStatement","argument":{"type":"Identifier","name":"profile","loc":{"start":{"line":162},"end":{"line":162}}},"loc":{"start":{"line":162},"end":{"line":162}}}],"loc":{"start":{"line":118},"end":{"line":163}}},"code":"\npublic Employee getEmployeeProfile_BACKUP(WebSession s, int userId, int subjectUserId) throws UnauthorizedException {\n    Employee profile \u003d null;\n    try {\n        String query \u003d \"SELECT * FROM employee WHERE userid \u003d ?\";\n        try {\n            PreparedStatement answer_statement \u003d WebSession.getConnection(s).prepareStatement(query, ResultSet.TYPE_SCROLL_INSENSITIVE, ResultSet.CONCUR_READ_ONLY);\n            answer_statement.setInt(1, subjectUserId);\n            ResultSet answer_results \u003d answer_statement.executeQuery();\n            if (answer_results.next()) {\n                profile \u003d new Employee(answer_results.getInt(\"userid\"), answer_results.getString(\"first_name\"), answer_results.getString(\"last_name\"), answer_results.getString(\"ssn\"), answer_results.getString(\"title\"), answer_results.getString(\"phone\"), answer_results.getString(\"address1\"), answer_results.getString(\"address2\"), answer_results.getInt(\"manager\"), answer_results.getString(\"start_date\"), answer_results.getInt(\"salary\"), answer_results.getString(\"ccn\"), answer_results.getInt(\"ccn_limit\"), answer_results.getString(\"disciplined_date\"), answer_results.getString(\"disciplined_notes\"), answer_results.getString(\"personal_description\"));\n            }\n        } catch (SQLException sqle) {\n            s.setMessage(\"Error getting employee profile\");\n            sqle.printStackTrace();\n        }\n    } catch (Exception e) {\n        s.setMessage(\"Error getting employee profile\");\n        e.printStackTrace();\n    }\n    return profile;\n}","loc":{"start":{"line":117},"end":{"line":163}}}],"loc":{"start":{"line":43},"end":{"line":165}}}],"loc":{"start":{"line":2},"end":{"line":165}},"sourcefile":"/Users/gli/codiscope/jacks.engine/WebGoat-5.4/WEB-INF/classes/org/owasp/webgoat/lessons/RoleBasedAccessControl/EditProfile.java"}